datasette_sqlite_robotstxt/__init__.py
datasette_sqlite_robotstxt/version.py
datasette_sqlite_robotstxt-0.1.0a62.dist-info/METADATA
datasette_sqlite_robotstxt-0.1.0a62.dist-info/WHEEL
datasette_sqlite_robotstxt-0.1.0a62.dist-info/entry_points.txt
datasette_sqlite_robotstxt-0.1.0a62.dist-info/top_level.txt
datasette_sqlite_robotstxt-0.1.0a62.dist-info/RECORD
