Metadata-Version: 2.1
Name: datasette-sqlite-robotstxt
Version: 0.1.0a62
Home-page: https://github.com/asg017/sqlite-robotstxt
Author: Alex Garcia
License: MIT License, Apache License, Version 2.0
Project-URL: Issues, https://github.com/asg017/sqlite-robotstxt/issues
Project-URL: CI, https://github.com/asg017/sqlite-robotstxt/actions
Project-URL: Changelog, https://github.com/asg017/sqlite-robotstxt/releases
Requires-Python: >=3.6
Requires-Dist: datasette
Requires-Dist: sqlite-robotstxt
Provides-Extra: test
Requires-Dist: pytest ; extra == 'test'
